.travis.yml
AUTHORS
ChangeLog
LICENSE
MANIFEST.in
README.rst
requirements.txt
setup.cfg
setup.py
setup_hooks.py
test-requirements.txt
jiractl/__init__.py
jiractl/app.py
jiractl.egg-info/PKG-INFO
jiractl.egg-info/SOURCES.txt
jiractl.egg-info/dependency_links.txt
jiractl.egg-info/entry_points.txt
jiractl.egg-info/not-zip-safe
jiractl.egg-info/pbr.json
jiractl.egg-info/requires.txt
jiractl.egg-info/top_level.txt
jiractl/commands/__init__.py
jiractl/commands/base.py
jiractl/commands/comments.py
jiractl/commands/issues.py
jiractl/commands/labels.py
jiractl/commands/links.py
tests/__init__.py
tests/base.py
tests/test_comments.py
tests/test_issues.py
tests/test_labels.py
tests/test_links.py