Metadata-Version: 1.1
Name: jiractl
Version: 0.0.6
Summary: The command line interface for Jira REST API
Home-page: https://github.com/bgaifullin/python-jiractl.git
Author: Bulat Gaifullin
Author-email: gaifullinbf@gmail.com
License: MIT
Keywords: jira
Platform: UNKNOWN
Classifier: Development Status :: 4 - Beta
Classifier: Intended Audience :: Information Technology
Classifier: Intended Audience :: System Administrators
Classifier: License :: OSI Approved :: MIT License
Classifier: Operating System :: POSIX :: Linux
Classifier: Programming Language :: Python
Classifier: Programming Language :: Python :: 2
Classifier: Programming Language :: Python :: 2.7
Classifier: Topic :: Utilities
